{
  "metricsProfile": {
    "name": "office365-profile-1",
    "profileType": "office365",
    "isTemplate": true,
    "metrics": [
      {
        "name": "onedrive.total",
        "customName": "",
        "description": "One Drive Total Disk Space",
        "monitored": true,
        "graphed": true,
        "metricType": "Gauge",
        "computeType": "Query",
        "serviceType": "OneDrive",
        "sourceType": "built-in",
        "aggregateType": "",
        "warningThreshold": -1,
        "criticalThreshold": -1,
        "expression": "$.quota.total",
        "format": "",
        "filters": [],
        "extensions": {}
      },
      {
        "name": "onedrive.total",
        "customName": "",
        "description": "One Drive Total Disk Space",
        "monitored": true,
        "graphed": true,
        "metricType": "Gauge",
        "computeType": "Query",
        "serviceType": "OneDrive",
        "sourceType": "built-in",
        "aggregateType": "",
        "warningThreshold": -1,
        "criticalThreshold": -1,
        "expression": "$.quota.total",
        "format": "",
        "filters": [],
        "extensions": {}
      },
      {
        "name": "onedrive.remaining",
        "customName": "",
        "description": "",
        "monitored": true,
        "graphed": true,
        "metricType": "Gauge",
        "computeType": "Query",
        "serviceType": "OneDrive",
        "sourceType": "built-in",
        "aggregateType": "",
        "warningThreshold": -1,
        "criticalThreshold": -1,
        "expression": "$.quota.remaining",
        "format": "",
        "filters": [],
        "extensions": {}
      },
      {
        "name": "onedrive.free",
        "customName": "",
        "description": "Percentage of One Drive free",
        "monitored": true,
        "graphed": true,
        "metricType": "Gauge",
        "computeType": "Query",
        "serviceType": "OneDrive",
        "sourceType": "built-in",
        "aggregateType": "",
        "warningThreshold": 15,
        "criticalThreshold": 5,
        "expression": "",
        "format": "",
        "filters": [],
        "extensions": {}
      },
      {
        "name": "$params.sharepoint",
        "customName": "",
        "description": "SharePoint Parameter holder",
        "monitored": false,
        "graphed": false,
        "metricType": "",
        "computeType": "Param",
        "serviceType": "SharePoint",
        "sourceType": "built-in",
        "aggregateType": "",
        "warningThreshold": -1,
        "criticalThreshold": -1,
        "expression": "https://graph.microsoft.com/v1.0/sites/%s:/sites/%s:/drives",
        "format": "",
        "filters": [],
        "extensions": {
          "SHAREPOINT_SITE": "",
          "SHAREPOINT_SUBSITE": ""
        }
      },
      {
        "name": "sharepoint.total",
        "customName": "",
        "description": "Share Point Total Disk Space Per Drive",
        "monitored": true,
        "graphed": true,
        "metricType": "Gauge",
        "computeType": "Query",
        "serviceType": "SharePoint",
        "sourceType": "built-in",
        "aggregateType": "",
        "warningThreshold": -1,
        "criticalThreshold": -1,
        "expression": "$.value[%d].total",
        "format": "",
        "filters": [],
        "extensions": {}
      },
      {
        "name": "sharepoint.remaining",
        "customName": "",
        "description": "Share Point Disk Space Remaining Pe",
        "monitored": true,
        "graphed": true,
        "metricType": "Gauge",
        "computeType": "Query",
        "serviceType": "SharePoint",
        "sourceType": "built-in",
        "aggregateType": "",
        "warningThreshold": -1,
        "criticalThreshold": -1,
        "expression": "$.value[%d].quota.remaining",
        "format": "",
        "filters": [],
        "extensions": {}
      },
      {
        "name": "sharepoint.free",
        "customName": "",
        "description": "Percentage of free space per Share Point drive",
        "monitored": true,
        "graphed": true,
        "metricType": "Gauge",
        "computeType": "Query",
        "serviceType": "SharePoint",
        "sourceType": "built-in",
        "aggregateType": "",
        "warningThreshold": 15,
        "criticalThreshold": 5,
        "expression": "",
        "format": "",
        "filters": [],
        "extensions": {}
      },
      {
        "name": "subscriptions.prepaid",
        "customName": "",
        "description": "Subscriptions Prepaid Count",
        "monitored": true,
        "graphed": true,
        "metricType": "Gauge",
        "computeType": "Query",
        "serviceType": "Licensing",
        "sourceType": "built-in",
        "aggregateType": "",
        "warningThreshold": -1,
        "criticalThreshold": -1,
        "expression": "$.value[%d].prepaidUnits.enabled",
        "format": "",
        "filters": [],
        "extensions": {}
      },
      {
        "name": "subscriptions.consumed",
        "customName": "",
        "description": "Subscriptions Consumed Count",
        "monitored": true,
        "graphed": true,
        "metricType": "Gauge",
        "computeType": "Query",
        "serviceType": "Licensing",
        "sourceType": "built-in",
        "aggregateType": "",
        "warningThreshold": -1,
        "criticalThreshold": -1,
        "expression": "$.value[%d].consumedUnits",
        "format": "",
        "filters": [],
        "extensions": {}
      },
      {
        "name": "unread.emails",
        "customName": "",
        "description": "Microsoft Office Unread Emails",
        "monitored": true,
        "graphed": true,
        "metricType": "Gauge",
        "computeType": "Query",
        "serviceType": "Email",
        "sourceType": "built-in",
        "aggregateType": "",
        "warningThreshold": 5,
        "criticalThreshold": 10,
        "expression": "",
        "format": "",
        "filters": [],
        "extensions": {}
      }
    ]
  },
  "monitorConnection": {
    "id": 222,
    "server": "test",
    "userName": "1",
    "password": "2",
    "sslEnabled": false,
    "url": "3",
    "views": [],
    "extensions": {"officeTenantId":  "dont store in git!", "officeClientId":  "TODO2", "officeClientSecret":  "SECRET"},
    "connectorId": 333
  }
}
